trajectory_executor/__init__.py
trajectory_executor/trajectory.py
trajectory_executor/trajectory_executor.py
trajectory_executor-0.2.0.dist-info/licenses/LICENSE
trajectory_executor-0.2.0.dist-info/METADATA
trajectory_executor-0.2.0.dist-info/WHEEL
trajectory_executor-0.2.0.dist-info/top_level.txt
trajectory_executor-0.2.0.dist-info/RECORD
