Metadata-Version: 2.4
Name: trajectory-executor
Version: 0.2.0
Summary: A lightweight executor for offline, time-based joint trajectories in robotic applications.
Author-email: bxtbold <bxtbold@protonmail.com>
License: MIT License
Project-URL: Homepage, https://github.com/bxtbold/trajectory-executor
Project-URL: Repository, https://github.com/bxtbold/trajectory-executor
Project-URL: Issues, https://github.com/bxtbold/trajectory-executor/issues
Classifier: Programming Language :: Python :: 3
Classifier: Programming Language :: Python :: 3.10
Classifier: Programming Language :: Python :: 3.11
Classifier: License :: OSI Approved :: MIT License
Classifier: Operating System :: OS Independent
Classifier: Intended Audience :: Developers
Classifier: Intended Audience :: Science/Research
Classifier: Framework :: Robot Framework :: Tool
Requires-Python: >=3.10
License-File: LICENSE
Requires-Dist: loop-rate-limiters>=1.1.0
Requires-Dist: numpy>=1.26.4
Provides-Extra: test
Requires-Dist: pytest>=8.0.0; extra == "test"
Requires-Dist: pytest-mock>=3.14.0; extra == "test"
Requires-Dist: pytest-cov>=5.0.0; extra == "test"
Requires-Dist: mujoco>=3.2.4; extra == "test"
Requires-Dist: torch; extra == "test"
Requires-Dist: genesis-world==0.2.1; extra == "test"
Provides-Extra: dev
Requires-Dist: black>=24.8.0; extra == "dev"
Requires-Dist: flake8>=7.1.1; extra == "dev"
Requires-Dist: pre-commit>=3.8.0; extra == "dev"
Requires-Dist: trajectory-executor[test]; extra == "dev"
Dynamic: license-file
